Workbook

Sheet Summary
A1: ILA Hub — 6-month revenue model, Daniel as sole provider
A2: Oct 2026 – Mar 2027 · 18–22 slots/week · prices £150 Essential / £190 Priority · built 26 Sep 2026 from live case data
A4: Net delivered revenue by month (£)
A5: Scenario | B5: Oct-26 | C5: Nov-26 | D5: Dec-26 | E5: Jan-27 | F5: Feb-27 | G5: Mar-27 | H5: 6-mo total
A6: Low — 18 slots/wk | B6: =Model!B17 | C6: =Model!C17 | D6: =Model!D17 | E6: =Model!E17 | F6: =Model!F17 | G6: =Model!G17 | H6: =Model!H17
A7: Base — 20 slots/wk | B7: =Model!B47 | C7: =Model!C47 | D7: =Model!D47 | E7: =Model!E47 | F7: =Model!F47 | G7: =Model!G47 | H7: =Model!H47
A8: High — 22 slots/wk | B8: =Model!B77 | C8: =Model!C77 | D8: =Model!D77 | E8: =Model!E77 | F8: =Model!F77 | G8: =Model!G77 | H8: =Model!H77
A10: Key outputs
A11: Metric | B11: Low | C11: Base | D11: High
A12: Paid cases (6 months) | B12: =Model!H9 | C12: =Model!H39 | D12: =Model!H69
A13: Delivered cases (6 months) | B13: =Model!H29 | C13: =Model!H59 | D13: =Model!H89
A14: Average monthly net delivered revenue (£) | B14: =AVERAGE(Model!B17:G17) | C14: =AVERAGE(Model!B47:G47) | D14: =AVERAGE(Model!B77:G77)
A15: March 2027 run-rate (£/month) | B15: =Model!G17 | C15: =Model!G47 | D15: =Model!G77
A16: Refunds (6 months, £) | B16: =Model!H16 | C16: =Model!H46 | D16: =Model!H76
A17: Direct platform costs (6 months, £) | B17: =Model!H22 | C17: =Model!H52 | D17: =Model!H82
A18: Marketing (6 months, £) | B18: =Model!H24 | C18: =Model!H54 | D18: =Model!H84
A19: Distributable net (6 months, £) | B19: =Model!H25 | C19: =Model!H55 | D19: =Model!H85
A20: Daniel 60% (6 months, £) | B20: =Model!H26 | C20: =Model!H56 | D20: =Model!H86
A21: Rona 40% (6 months, £) | B21: =Model!H27 | C21: =Model!H57 | D21: =Model!H87
A22: Daniel hours / week (average) | B22: =Model!H30 | C22: =Model!H60 | D22: =Model!H90
A23: Daniel hours / week (March) | B23: =Model!G30 | C23: =Model!G60 | D23: =Model!G90
A24: Annualised run-rate vs £90k VAT threshold | B24: =Model!G17*12 | C24: =Model!G47*12 | D24: =Model!G77*12
A25: First month at £6k milestone | B25: =IFERROR(INDEX(Model!$B$4:$G$4,MATCH("Yes",Model!B31:G31,0)),"Not in window") | C25: =IFERROR(INDEX(Model!$B$34:$G$34,MATCH("Yes",Model!B61:G61,0)),"Not in window") | D25: =IFERROR(INDEX(Model!$B$64:$G$64,MATCH("Yes",Model!B91:G91,0)),"Not in window")
A28: How to read this
A29: Capacity is not the constraint, fill is. 20 slots x 4.3 weeks x £150 is ~£12.9k/month gross at 100% fill; actual fill since mid-August is 30-45%. Even High keeps Daniel under 10 hours a week of ILA work.
A30: Low (18 slots, fill 40-60%, refunds 15%) tracks today's run-rate: ~£5k/month, clears £6k only in March. Base (20 slots, fill 50-80%, refunds 10%) clears £6k from October, dips in December, reaches £10k in March. High (22 slots, fill 60-90%) clears £10k from January.
A31: Refunds are the biggest controllable leak: 13% by count since August, 20.7% lifetime by value. Each 5 points of refund rate is worth ~£400/month at Base volumes. The lender library and pack-check intake are the fixes.
A32: VAT risk: Base annualises to ~£121k by March, above the £90k rolling-12-month threshold. Registration is likely due in Q1 2027 on Base or High. VAT on £150 either cuts net 17% or moves the price to £180; decide before January.
A33: December is deliberately thin (3.0 working weeks). If Daniel works through Christmas, set Dec weeks to 4.4 and Base adds ~£2.6k.
A34: Change the yellow cells on Assumptions to re-run. Slots/week, fill ramp and refund rate drive more than 90% of the outcome. Formulas recalculate when the file opens in Excel or Google Sheets.

Sheet Assumptions
A1: ILA Hub — Revenue model assumptions (Oct 2026 – Mar 2027)
A2: Legend: blue = input you can change · black = formula · green = link to another sheet · yellow = key lever. Single provider: Daniel McAfee.
A3: Global inputs
A4: Essential price (£) | B4: 150 | M4: Live Stripe price. Granola catch-ups Sep 2026: £150 standard 'well received'.
A5: Priority price (£) | B5: 190 | M5: Daniel email 23 Sep 2026 'New priority price ID' — £190 (down from £249/£250).
A6: Wet-signature / postal add-on (£) | B6: 25 | M6: £25 opt-in, to be charged upfront (Sep catch-ups).
A7: Stripe fee — % of takings | B7: 0.015 | M7: PRD §2: Stripe ~1.5–2.5%. UK card rate 1.5% + 20p used.
A8: Stripe fee — fixed per payment (£) | B8: 0.2 | M8: UK Stripe fixed fee.
A9: E-signature cost per case (£) | B9: 1.5 | M9: Dropbox Sign envelope, estimate.
A10: AI prep cost per case (£) | B10: 0.1 | M10: PRD: Claude API ~£0.05/case; rounded up.
A11: Special-delivery postage per wet-sign case (£) | B11: 10 | M11: Sep catch-ups: postage ~£10; Royal Mail business account.
A12: Daniel share of net | B12: 0.6 | M12: PRD §2: 60% Daniel / 40% Rona on net after direct platform costs; marketing off the top.
A13: Rona share of net | B13: =1-B12
A14: Daniel minutes per case (call + review + certificate) | B14: 30 | M14: Calls 10–15 min (Sep catch-ups); dashboard target 30–45 min all-in. 30 used.
A15: VAT registration threshold (£, rolling 12 months) | B15: 90000 | M15: PRD §2. Renegotiate split at threshold.
A16: Milestone 1 — monthly net delivered revenue (£) | B16: 6000 | M16: Sep catch-ups / Business dashboard.
A17: Milestone 2 — monthly net delivered revenue (£) | B17: 10000 | M17: Sep catch-ups / Business dashboard.
A19: Calendar
A20: Month | B20: Oct-26 | C20: Nov-26 | D20: Dec-26 | E20: Jan-27 | F20: Feb-27 | G20: Mar-27 | H20: Total
A21: Working weeks in month (Daniel available) | B21: 4.4 | C21: 4.2 | D21: 3 | E21: 4.2 | F21: 4 | G21: 4.4 | H21: =SUM(B21:G21) | M21: Weekdays ÷ 5, less bank holidays. Dec assumes ~1.5 weeks off over Christmas. Sat/Sun slots exist today but are folded into the weekly slot count.
A23: Scenario levers
A24: Scenario | B24: Slots / week | C24: Fill Oct | D24: Fill Nov | E24: Fill Dec | F24: Fill Jan | G24: Fill Feb | H24: Fill Mar | I24: Priority mix | J24: Refund rate | K24: Wet-sign uptake | L24: Ads spend / month (£)
A25: Low | B25: 18 | C25: 0.4 | D25: 0.45 | E25: 0.5 | F25: 0.55 | G25: 0.55 | H25: 0.6 | I25: 0.05 | J25: 0.15 | K25: 0.25 | L25: 0
A26: Base | B26: 20 | C26: 0.5 | D26: 0.6 | E26: 0.65 | F26: 0.7 | G26: 0.75 | H26: 0.8 | I26: 0.1 | J26: 0.1 | K26: 0.25 | L26: 360
A27: High | B27: 22 | C27: 0.6 | D27: 0.7 | E27: 0.75 | F27: 0.85 | G27: 0.9 | H27: 0.9 | I27: 0.15 | J27: 0.07 | K27: 0.25 | L27: 600
A29: Fill = paid bookings ÷ available slots. Calibration (Actuals sheet): 17 Aug–21 Sep averaged ~9 paid/week = ~45% of 20 slots; last 3 weeks ~6/week = 30%.
A30: Refund rate by count: 7 of ~52 paid cases since 1 Aug = 13%; lifetime by value 20.7% (Business dashboard). Low holds 15%; Base assumes intake/lender-library fixes cut it to 10%; High 7%.
A31: Priority mix: only 1 Priority booking since the £150/£190 repricing. Low 5%, Base 10%, High 15% assumes the £190 point is tested and marketed.
A32: Slots/week = your stated 18–22 range. Low 18, Base 20, High 22.
A33: Ads: Sep catch-ups — ~£8 cost per transaction, spend reinstated up to £12/day (~£360/month), scaling paused. High assumes £20/day.
A34: No-shows are non-refundable (PRD refund policy) so they stay in revenue; unpaid holds never count as paid so they are excluded by construction.

Sheet Model
A1: ILA Hub — monthly revenue model by scenario (Daniel only)
A2: All figures £ unless stated. Every cell is a formula off the Assumptions sheet.
A4: Low scenario | B4: Oct-26 | C4: Nov-26 | D4: Dec-26 | E4: Jan-27 | F4: Feb-27 | G4: Mar-27 | H4: 6-mo total
A5: Working weeks | B5: =Assumptions!B$21 | C5: =Assumptions!C$21 | D5: =Assumptions!D$21 | E5: =Assumptions!E$21 | F5: =Assumptions!F$21 | G5: =Assumptions!G$21 | H5: =SUM(B5:G5)
A6: Slots per week | B6: =Assumptions!$B$25 | C6: =Assumptions!$B$25 | D6: =Assumptions!$B$25 | E6: =Assumptions!$B$25 | F6: =Assumptions!$B$25 | G6: =Assumptions!$B$25
A7: Slots available | B7: =B5*B6 | C7: =C5*C6 | D7: =D5*D6 | E7: =E5*E6 | F7: =F5*F6 | G7: =G5*G6 | H7: =SUM(B7:G7)
A8: Fill rate (paid bookings ÷ slots) | B8: =Assumptions!C$25 | C8: =Assumptions!D$25 | D8: =Assumptions!E$25 | E8: =Assumptions!F$25 | F8: =Assumptions!G$25 | G8: =Assumptions!H$25 | H8: =AVERAGE(B8:G8)
A9: Paid cases | B9: =ROUND(B7*B8,0) | C9: =ROUND(C7*C8,0) | D9: =ROUND(D7*D8,0) | E9: =ROUND(E7*E8,0) | F9: =ROUND(F7*F8,0) | G9: =ROUND(G7*G8,0) | H9: =SUM(B9:G9)
A10: of which Priority | B10: =ROUND(B9*Assumptions!$I$25,0) | C10: =ROUND(C9*Assumptions!$I$25,0) | D10: =ROUND(D9*Assumptions!$I$25,0) | E10: =ROUND(E9*Assumptions!$I$25,0) | F10: =ROUND(F9*Assumptions!$I$25,0) | G10: =ROUND(G9*Assumptions!$I$25,0) | H10: =SUM(B10:G10)
A11: of which Essential | B11: =B9-B10 | C11: =C9-C10 | D11: =D9-D10 | E11: =E9-E10 | F11: =F9-F10 | G11: =G9-G10 | H11: =SUM(B11:G11)
A12: Wet-signature add-on cases | B12: =ROUND(B9*Assumptions!$K$25,0) | C12: =ROUND(C9*Assumptions!$K$25,0) | D12: =ROUND(D9*Assumptions!$K$25,0) | E12: =ROUND(E9*Assumptions!$K$25,0) | F12: =ROUND(F9*Assumptions!$K$25,0) | G12: =ROUND(G9*Assumptions!$K$25,0) | H12: =SUM(B12:G12)
A13: Service revenue (gross) | B13: =B11*Assumptions!$B$4+B10*Assumptions!$B$5 | C13: =C11*Assumptions!$B$4+C10*Assumptions!$B$5 | D13: =D11*Assumptions!$B$4+D10*Assumptions!$B$5 | E13: =E11*Assumptions!$B$4+E10*Assumptions!$B$5 | F13: =F11*Assumptions!$B$4+F10*Assumptions!$B$5 | G13: =G11*Assumptions!$B$4+G10*Assumptions!$B$5 | H13: =SUM(B13:G13)
A14: Add-on revenue | B14: =B12*Assumptions!$B$6 | C14: =C12*Assumptions!$B$6 | D14: =D12*Assumptions!$B$6 | E14: =E12*Assumptions!$B$6 | F14: =F12*Assumptions!$B$6 | G14: =G12*Assumptions!$B$6 | H14: =SUM(B14:G14)
A15: Gross bookings | B15: =B13+B14 | C15: =C13+C14 | D15: =D13+D14 | E15: =E13+E14 | F15: =F13+F14 | G15: =G13+G14 | H15: =SUM(B15:G15)
A16: Refunds | B16: =-ROUND(B15*Assumptions!$J$25,0) | C16: =-ROUND(C15*Assumptions!$J$25,0) | D16: =-ROUND(D15*Assumptions!$J$25,0) | E16: =-ROUND(E15*Assumptions!$J$25,0) | F16: =-ROUND(F15*Assumptions!$J$25,0) | G16: =-ROUND(G15*Assumptions!$J$25,0) | H16: =SUM(B16:G16)
A17: Net delivered revenue | B17: =B15+B16 | C17: =C15+C16 | D17: =D15+D16 | E17: =E15+E16 | F17: =F15+F16 | G17: =G15+G16 | H17: =SUM(B17:G17)
A18: Stripe fees | B18: =-(B15*Assumptions!$B$7+B9*Assumptions!$B$8) | C18: =-(C15*Assumptions!$B$7+C9*Assumptions!$B$8) | D18: =-(D15*Assumptions!$B$7+D9*Assumptions!$B$8) | E18: =-(E15*Assumptions!$B$7+E9*Assumptions!$B$8) | F18: =-(F15*Assumptions!$B$7+F9*Assumptions!$B$8) | G18: =-(G15*Assumptions!$B$7+G9*Assumptions!$B$8) | H18: =SUM(B18:G18)
A19: E-signature | B19: =-B9*Assumptions!$B$9 | C19: =-C9*Assumptions!$B$9 | D19: =-D9*Assumptions!$B$9 | E19: =-E9*Assumptions!$B$9 | F19: =-F9*Assumptions!$B$9 | G19: =-G9*Assumptions!$B$9 | H19: =SUM(B19:G19)
A20: AI prep | B20: =-B9*Assumptions!$B$10 | C20: =-C9*Assumptions!$B$10 | D20: =-D9*Assumptions!$B$10 | E20: =-E9*Assumptions!$B$10 | F20: =-F9*Assumptions!$B$10 | G20: =-G9*Assumptions!$B$10 | H20: =SUM(B20:G20)
A21: Postage (wet-sign cases) | B21: =-B12*Assumptions!$B$11 | C21: =-C12*Assumptions!$B$11 | D21: =-D12*Assumptions!$B$11 | E21: =-E12*Assumptions!$B$11 | F21: =-F12*Assumptions!$B$11 | G21: =-G12*Assumptions!$B$11 | H21: =SUM(B21:G21)
A22: Total direct platform costs | B22: =SUM(B18:B21) | C22: =SUM(C18:C21) | D22: =SUM(D18:D21) | E22: =SUM(E18:E21) | F22: =SUM(F18:F21) | G22: =SUM(G18:G21) | H22: =SUM(B22:G22)
A23: Net after direct costs | B23: =B17+B22 | C23: =C17+C22 | D23: =D17+D22 | E23: =E17+E22 | F23: =F17+F22 | G23: =G17+G22 | H23: =SUM(B23:G23)
A24: Marketing (off the top) | B24: =-Assumptions!$L$25 | C24: =-Assumptions!$L$25 | D24: =-Assumptions!$L$25 | E24: =-Assumptions!$L$25 | F24: =-Assumptions!$L$25 | G24: =-Assumptions!$L$25 | H24: =SUM(B24:G24)
A25: Distributable net | B25: =B23+B24 | C25: =C23+C24 | D25: =D23+D24 | E25: =E23+E24 | F25: =F23+F24 | G25: =G23+G24 | H25: =SUM(B25:G25)
A26: Daniel (60%) | B26: =B25*Assumptions!$B$12 | C26: =C25*Assumptions!$B$12 | D26: =D25*Assumptions!$B$12 | E26: =E25*Assumptions!$B$12 | F26: =F25*Assumptions!$B$12 | G26: =G25*Assumptions!$B$12 | H26: =SUM(B26:G26)
A27: Rona (40%) | B27: =B25*Assumptions!$B$13 | C27: =C25*Assumptions!$B$13 | D27: =D25*Assumptions!$B$13 | E27: =E25*Assumptions!$B$13 | F27: =F25*Assumptions!$B$13 | G27: =G25*Assumptions!$B$13 | H27: =SUM(B27:G27)
A28: Cumulative net delivered revenue | B28: =B17 | C28: =B28+C17 | D28: =C28+D17 | E28: =D28+E17 | F28: =E28+F17 | G28: =F28+G17
A29: Delivered cases (paid less refunded) | B29: =B9+ROUND(B16/Assumptions!$B$4,0) | C29: =C9+ROUND(C16/Assumptions!$B$4,0) | D29: =D9+ROUND(D16/Assumptions!$B$4,0) | E29: =E9+ROUND(E16/Assumptions!$B$4,0) | F29: =F9+ROUND(F16/Assumptions!$B$4,0) | G29: =G9+ROUND(G16/Assumptions!$B$4,0) | H29: =SUM(B29:G29)
A30: Daniel hours per week | B30: =IF(B5=0,0,B9*Assumptions!$B$14/60/B5) | C30: =IF(C5=0,0,C9*Assumptions!$B$14/60/C5) | D30: =IF(D5=0,0,D9*Assumptions!$B$14/60/D5) | E30: =IF(E5=0,0,E9*Assumptions!$B$14/60/E5) | F30: =IF(F5=0,0,F9*Assumptions!$B$14/60/F5) | G30: =IF(G5=0,0,G9*Assumptions!$B$14/60/G5) | H30: =AVERAGE(B30:G30)
A31: Hits £6k milestone? | B31: =IF(B17>=Assumptions!$B$16,"Yes","No") | C31: =IF(C17>=Assumptions!$B$16,"Yes","No") | D31: =IF(D17>=Assumptions!$B$16,"Yes","No") | E31: =IF(E17>=Assumptions!$B$16,"Yes","No") | F31: =IF(F17>=Assumptions!$B$16,"Yes","No") | G31: =IF(G17>=Assumptions!$B$16,"Yes","No")
A34: Base scenario | B34: Oct-26 | C34: Nov-26 | D34: Dec-26 | E34: Jan-27 | F34: Feb-27 | G34: Mar-27 | H34: 6-mo total
A35: Working weeks | B35: =Assumptions!B$21 | C35: =Assumptions!C$21 | D35: =Assumptions!D$21 | E35: =Assumptions!E$21 | F35: =Assumptions!F$21 | G35: =Assumptions!G$21 | H35: =SUM(B35:G35)
A36: Slots per week | B36: =Assumptions!$B$26 | C36: =Assumptions!$B$26 | D36: =Assumptions!$B$26 | E36: =Assumptions!$B$26 | F36: =Assumptions!$B$26 | G36: =Assumptions!$B$26
A37: Slots available | B37: =B35*B36 | C37: =C35*C36 | D37: =D35*D36 | E37: =E35*E36 | F37: =F35*F36 | G37: =G35*G36 | H37: =SUM(B37:G37)
A38: Fill rate (paid bookings ÷ slots) | B38: =Assumptions!C$26 | C38: =Assumptions!D$26 | D38: =Assumptions!E$26 | E38: =Assumptions!F$26 | F38: =Assumptions!G$26 | G38: =Assumptions!H$26 | H38: =AVERAGE(B38:G38)
A39: Paid cases | B39: =ROUND(B37*B38,0) | C39: =ROUND(C37*C38,0) | D39: =ROUND(D37*D38,0) | E39: =ROUND(E37*E38,0) | F39: =ROUND(F37*F38,0) | G39: =ROUND(G37*G38,0) | H39: =SUM(B39:G39)
A40: of which Priority | B40: =ROUND(B39*Assumptions!$I$26,0) | C40: =ROUND(C39*Assumptions!$I$26,0) | D40: =ROUND(D39*Assumptions!$I$26,0) | E40: =ROUND(E39*Assumptions!$I$26,0) | F40: =ROUND(F39*Assumptions!$I$26,0) | G40: =ROUND(G39*Assumptions!$I$26,0) | H40: =SUM(B40:G40)
A41: of which Essential | B41: =B39-B40 | C41: =C39-C40 | D41: =D39-D40 | E41: =E39-E40 | F41: =F39-F40 | G41: =G39-G40 | H41: =SUM(B41:G41)
A42: Wet-signature add-on cases | B42: =ROUND(B39*Assumptions!$K$26,0) | C42: =ROUND(C39*Assumptions!$K$26,0) | D42: =ROUND(D39*Assumptions!$K$26,0) | E42: =ROUND(E39*Assumptions!$K$26,0) | F42: =ROUND(F39*Assumptions!$K$26,0) | G42: =ROUND(G39*Assumptions!$K$26,0) | H42: =SUM(B42:G42)
A43: Service revenue (gross) | B43: =B41*Assumptions!$B$4+B40*Assumptions!$B$5 | C43: =C41*Assumptions!$B$4+C40*Assumptions!$B$5 | D43: =D41*Assumptions!$B$4+D40*Assumptions!$B$5 | E43: =E41*Assumptions!$B$4+E40*Assumptions!$B$5 | F43: =F41*Assumptions!$B$4+F40*Assumptions!$B$5 | G43: =G41*Assumptions!$B$4+G40*Assumptions!$B$5 | H43: =SUM(B43:G43)
A44: Add-on revenue | B44: =B42*Assumptions!$B$6 | C44: =C42*Assumptions!$B$6 | D44: =D42*Assumptions!$B$6 | E44: =E42*Assumptions!$B$6 | F44: =F42*Assumptions!$B$6 | G44: =G42*Assumptions!$B$6 | H44: =SUM(B44:G44)
A45: Gross bookings | B45: =B43+B44 | C45: =C43+C44 | D45: =D43+D44 | E45: =E43+E44 | F45: =F43+F44 | G45: =G43+G44 | H45: =SUM(B45:G45)
A46: Refunds | B46: =-ROUND(B45*Assumptions!$J$26,0) | C46: =-ROUND(C45*Assumptions!$J$26,0) | D46: =-ROUND(D45*Assumptions!$J$26,0) | E46: =-ROUND(E45*Assumptions!$J$26,0) | F46: =-ROUND(F45*Assumptions!$J$26,0) | G46: =-ROUND(G45*Assumptions!$J$26,0) | H46: =SUM(B46:G46)
A47: Net delivered revenue | B47: =B45+B46 | C47: =C45+C46 | D47: =D45+D46 | E47: =E45+E46 | F47: =F45+F46 | G47: =G45+G46 | H47: =SUM(B47:G47)
A48: Stripe fees | B48: =-(B45*Assumptions!$B$7+B39*Assumptions!$B$8) | C48: =-(C45*Assumptions!$B$7+C39*Assumptions!$B$8) | D48: =-(D45*Assumptions!$B$7+D39*Assumptions!$B$8) | E48: =-(E45*Assumptions!$B$7+E39*Assumptions!$B$8) | F48: =-(F45*Assumptions!$B$7+F39*Assumptions!$B$8) | G48: =-(G45*Assumptions!$B$7+G39*Assumptions!$B$8) | H48: =SUM(B48:G48)
A49: E-signature | B49: =-B39*Assumptions!$B$9 | C49: =-C39*Assumptions!$B$9 | D49: =-D39*Assumptions!$B$9 | E49: =-E39*Assumptions!$B$9 | F49: =-F39*Assumptions!$B$9 | G49: =-G39*Assumptions!$B$9 | H49: =SUM(B49:G49)
A50: AI prep | B50: =-B39*Assumptions!$B$10 | C50: =-C39*Assumptions!$B$10 | D50: =-D39*Assumptions!$B$10 | E50: =-E39*Assumptions!$B$10 | F50: =-F39*Assumptions!$B$10 | G50: =-G39*Assumptions!$B$10 | H50: =SUM(B50:G50)
A51: Postage (wet-sign cases) | B51: =-B42*Assumptions!$B$11 | C51: =-C42*Assumptions!$B$11 | D51: =-D42*Assumptions!$B$11 | E51: =-E42*Assumptions!$B$11 | F51: =-F42*Assumptions!$B$11 | G51: =-G42*Assumptions!$B$11 | H51: =SUM(B51:G51)
A52: Total direct platform costs | B52: =SUM(B48:B51) | C52: =SUM(C48:C51) | D52: =SUM(D48:D51) | E52: =SUM(E48:E51) | F52: =SUM(F48:F51) | G52: =SUM(G48:G51) | H52: =SUM(B52:G52)
A53: Net after direct costs | B53: =B47+B52 | C53: =C47+C52 | D53: =D47+D52 | E53: =E47+E52 | F53: =F47+F52 | G53: =G47+G52 | H53: =SUM(B53:G53)
A54: Marketing (off the top) | B54: =-Assumptions!$L$26 | C54: =-Assumptions!$L$26 | D54: =-Assumptions!$L$26 | E54: =-Assumptions!$L$26 | F54: =-Assumptions!$L$26 | G54: =-Assumptions!$L$26 | H54: =SUM(B54:G54)
A55: Distributable net | B55: =B53+B54 | C55: =C53+C54 | D55: =D53+D54 | E55: =E53+E54 | F55: =F53+F54 | G55: =G53+G54 | H55: =SUM(B55:G55)
A56: Daniel (60%) | B56: =B55*Assumptions!$B$12 | C56: =C55*Assumptions!$B$12 | D56: =D55*Assumptions!$B$12 | E56: =E55*Assumptions!$B$12 | F56: =F55*Assumptions!$B$12 | G56: =G55*Assumptions!$B$12 | H56: =SUM(B56:G56)
A57: Rona (40%) | B57: =B55*Assumptions!$B$13 | C57: =C55*Assumptions!$B$13 | D57: =D55*Assumptions!$B$13 | E57: =E55*Assumptions!$B$13 | F57: =F55*Assumptions!$B$13 | G57: =G55*Assumptions!$B$13 | H57: =SUM(B57:G57)
A58: Cumulative net delivered revenue | B58: =B47 | C58: =B58+C47 | D58: =C58+D47 | E58: =D58+E47 | F58: =E58+F47 | G58: =F58+G47
A59: Delivered cases (paid less refunded) | B59: =B39+ROUND(B46/Assumptions!$B$4,0) | C59: =C39+ROUND(C46/Assumptions!$B$4,0) | D59: =D39+ROUND(D46/Assumptions!$B$4,0) | E59: =E39+ROUND(E46/Assumptions!$B$4,0) | F59: =F39+ROUND(F46/Assumptions!$B$4,0) | G59: =G39+ROUND(G46/Assumptions!$B$4,0) | H59: =SUM(B59:G59)
A60: Daniel hours per week | B60: =IF(B35=0,0,B39*Assumptions!$B$14/60/B35) | C60: =IF(C35=0,0,C39*Assumptions!$B$14/60/C35) | D60: =IF(D35=0,0,D39*Assumptions!$B$14/60/D35) | E60: =IF(E35=0,0,E39*Assumptions!$B$14/60/E35) | F60: =IF(F35=0,0,F39*Assumptions!$B$14/60/F35) | G60: =IF(G35=0,0,G39*Assumptions!$B$14/60/G35) | H60: =AVERAGE(B60:G60)
A61: Hits £6k milestone? | B61: =IF(B47>=Assumptions!$B$16,"Yes","No") | C61: =IF(C47>=Assumptions!$B$16,"Yes","No") | D61: =IF(D47>=Assumptions!$B$16,"Yes","No") | E61: =IF(E47>=Assumptions!$B$16,"Yes","No") | F61: =IF(F47>=Assumptions!$B$16,"Yes","No") | G61: =IF(G47>=Assumptions!$B$16,"Yes","No")
A64: High scenario | B64: Oct-26 | C64: Nov-26 | D64: Dec-26 | E64: Jan-27 | F64: Feb-27 | G64: Mar-27 | H64: 6-mo total
A65: Working weeks | B65: =Assumptions!B$21 | C65: =Assumptions!C$21 | D65: =Assumptions!D$21 | E65: =Assumptions!E$21 | F65: =Assumptions!F$21 | G65: =Assumptions!G$21 | H65: =SUM(B65:G65)
A66: Slots per week | B66: =Assumptions!$B$27 | C66: =Assumptions!$B$27 | D66: =Assumptions!$B$27 | E66: =Assumptions!$B$27 | F66: =Assumptions!$B$27 | G66: =Assumptions!$B$27
A67: Slots available | B67: =B65*B66 | C67: =C65*C66 | D67: =D65*D66 | E67: =E65*E66 | F67: =F65*F66 | G67: =G65*G66 | H67: =SUM(B67:G67)
A68: Fill rate (paid bookings ÷ slots) | B68: =Assumptions!C$27 | C68: =Assumptions!D$27 | D68: =Assumptions!E$27 | E68: =Assumptions!F$27 | F68: =Assumptions!G$27 | G68: =Assumptions!H$27 | H68: =AVERAGE(B68:G68)
A69: Paid cases | B69: =ROUND(B67*B68,0) | C69: =ROUND(C67*C68,0) | D69: =ROUND(D67*D68,0) | E69: =ROUND(E67*E68,0) | F69: =ROUND(F67*F68,0) | G69: =ROUND(G67*G68,0) | H69: =SUM(B69:G69)
A70: of which Priority | B70: =ROUND(B69*Assumptions!$I$27,0) | C70: =ROUND(C69*Assumptions!$I$27,0) | D70: =ROUND(D69*Assumptions!$I$27,0) | E70: =ROUND(E69*Assumptions!$I$27,0) | F70: =ROUND(F69*Assumptions!$I$27,0) | G70: =ROUND(G69*Assumptions!$I$27,0) | H70: =SUM(B70:G70)
A71: of which Essential | B71: =B69-B70 | C71: =C69-C70 | D71: =D69-D70 | E71: =E69-E70 | F71: =F69-F70 | G71: =G69-G70 | H71: =SUM(B71:G71)
A72: Wet-signature add-on cases | B72: =ROUND(B69*Assumptions!$K$27,0) | C72: =ROUND(C69*Assumptions!$K$27,0) | D72: =ROUND(D69*Assumptions!$K$27,0) | E72: =ROUND(E69*Assumptions!$K$27,0) | F72: =ROUND(F69*Assumptions!$K$27,0) | G72: =ROUND(G69*Assumptions!$K$27,0) | H72: =SUM(B72:G72)
A73: Service revenue (gross) | B73: =B71*Assumptions!$B$4+B70*Assumptions!$B$5 | C73: =C71*Assumptions!$B$4+C70*Assumptions!$B$5 | D73: =D71*Assumptions!$B$4+D70*Assumptions!$B$5 | E73: =E71*Assumptions!$B$4+E70*Assumptions!$B$5 | F73: =F71*Assumptions!$B$4+F70*Assumptions!$B$5 | G73: =G71*Assumptions!$B$4+G70*Assumptions!$B$5 | H73: =SUM(B73:G73)
A74: Add-on revenue | B74: =B72*Assumptions!$B$6 | C74: =C72*Assumptions!$B$6 | D74: =D72*Assumptions!$B$6 | E74: =E72*Assumptions!$B$6 | F74: =F72*Assumptions!$B$6 | G74: =G72*Assumptions!$B$6 | H74: =SUM(B74:G74)
A75: Gross bookings | B75: =B73+B74 | C75: =C73+C74 | D75: =D73+D74 | E75: =E73+E74 | F75: =F73+F74 | G75: =G73+G74 | H75: =SUM(B75:G75)
A76: Refunds | B76: =-ROUND(B75*Assumptions!$J$27,0) | C76: =-ROUND(C75*Assumptions!$J$27,0) | D76: =-ROUND(D75*Assumptions!$J$27,0) | E76: =-ROUND(E75*Assumptions!$J$27,0) | F76: =-ROUND(F75*Assumptions!$J$27,0) | G76: =-ROUND(G75*Assumptions!$J$27,0) | H76: =SUM(B76:G76)
A77: Net delivered revenue | B77: =B75+B76 | C77: =C75+C76 | D77: =D75+D76 | E77: =E75+E76 | F77: =F75+F76 | G77: =G75+G76 | H77: =SUM(B77:G77)
A78: Stripe fees | B78: =-(B75*Assumptions!$B$7+B69*Assumptions!$B$8) | C78: =-(C75*Assumptions!$B$7+C69*Assumptions!$B$8) | D78: =-(D75*Assumptions!$B$7+D69*Assumptions!$B$8) | E78: =-(E75*Assumptions!$B$7+E69*Assumptions!$B$8) | F78: =-(F75*Assumptions!$B$7+F69*Assumptions!$B$8) | G78: =-(G75*Assumptions!$B$7+G69*Assumptions!$B$8) | H78: =SUM(B78:G78)
A79: E-signature | B79: =-B69*Assumptions!$B$9 | C79: =-C69*Assumptions!$B$9 | D79: =-D69*Assumptions!$B$9 | E79: =-E69*Assumptions!$B$9 | F79: =-F69*Assumptions!$B$9 | G79: =-G69*Assumptions!$B$9 | H79: =SUM(B79:G79)
A80: AI prep | B80: =-B69*Assumptions!$B$10 | C80: =-C69*Assumptions!$B$10 | D80: =-D69*Assumptions!$B$10 | E80: =-E69*Assumptions!$B$10 | F80: =-F69*Assumptions!$B$10 | G80: =-G69*Assumptions!$B$10 | H80: =SUM(B80:G80)
A81: Postage (wet-sign cases) | B81: =-B72*Assumptions!$B$11 | C81: =-C72*Assumptions!$B$11 | D81: =-D72*Assumptions!$B$11 | E81: =-E72*Assumptions!$B$11 | F81: =-F72*Assumptions!$B$11 | G81: =-G72*Assumptions!$B$11 | H81: =SUM(B81:G81)
A82: Total direct platform costs | B82: =SUM(B78:B81) | C82: =SUM(C78:C81) | D82: =SUM(D78:D81) | E82: =SUM(E78:E81) | F82: =SUM(F78:F81) | G82: =SUM(G78:G81) | H82: =SUM(B82:G82)
A83: Net after direct costs | B83: =B77+B82 | C83: =C77+C82 | D83: =D77+D82 | E83: =E77+E82 | F83: =F77+F82 | G83: =G77+G82 | H83: =SUM(B83:G83)
A84: Marketing (off the top) | B84: =-Assumptions!$L$27 | C84: =-Assumptions!$L$27 | D84: =-Assumptions!$L$27 | E84: =-Assumptions!$L$27 | F84: =-Assumptions!$L$27 | G84: =-Assumptions!$L$27 | H84: =SUM(B84:G84)
A85: Distributable net | B85: =B83+B84 | C85: =C83+C84 | D85: =D83+D84 | E85: =E83+E84 | F85: =F83+F84 | G85: =G83+G84 | H85: =SUM(B85:G85)
A86: Daniel (60%) | B86: =B85*Assumptions!$B$12 | C86: =C85*Assumptions!$B$12 | D86: =D85*Assumptions!$B$12 | E86: =E85*Assumptions!$B$12 | F86: =F85*Assumptions!$B$12 | G86: =G85*Assumptions!$B$12 | H86: =SUM(B86:G86)
A87: Rona (40%) | B87: =B85*Assumptions!$B$13 | C87: =C85*Assumptions!$B$13 | D87: =D85*Assumptions!$B$13 | E87: =E85*Assumptions!$B$13 | F87: =F85*Assumptions!$B$13 | G87: =G85*Assumptions!$B$13 | H87: =SUM(B87:G87)
A88: Cumulative net delivered revenue | B88: =B77 | C88: =B88+C77 | D88: =C88+D77 | E88: =D88+E77 | F88: =E88+F77 | G88: =F88+G77
A89: Delivered cases (paid less refunded) | B89: =B69+ROUND(B76/Assumptions!$B$4,0) | C89: =C69+ROUND(C76/Assumptions!$B$4,0) | D89: =D69+ROUND(D76/Assumptions!$B$4,0) | E89: =E69+ROUND(E76/Assumptions!$B$4,0) | F89: =F69+ROUND(F76/Assumptions!$B$4,0) | G89: =G69+ROUND(G76/Assumptions!$B$4,0) | H89: =SUM(B89:G89)
A90: Daniel hours per week | B90: =IF(B65=0,0,B69*Assumptions!$B$14/60/B65) | C90: =IF(C65=0,0,C69*Assumptions!$B$14/60/C65) | D90: =IF(D65=0,0,D69*Assumptions!$B$14/60/D65) | E90: =IF(E65=0,0,E69*Assumptions!$B$14/60/E65) | F90: =IF(F65=0,0,F69*Assumptions!$B$14/60/F65) | G90: =IF(G65=0,0,G69*Assumptions!$B$14/60/G65) | H90: =AVERAGE(B90:G90)
A91: Hits £6k milestone? | B91: =IF(B77>=Assumptions!$B$16,"Yes","No") | C91: =IF(C77>=Assumptions!$B$16,"Yes","No") | D91: =IF(D77>=Assumptions!$B$16,"Yes","No") | E91: =IF(E77>=Assumptions!$B$16,"Yes","No") | F91: =IF(F77>=Assumptions!$B$16,"Yes","No") | G91: =IF(G77>=Assumptions!$B$16,"Yes","No")

Sheet Actuals
A1: Actuals — weekly, from ILA Hub production database (cases table), pulled 26 Sep 2026
A2: Excludes internal/test cases. Week = Monday start. 'Paid £' = sum of service price on paid cases (before refunds). Delivered = final_delivered_at set.
A4: Week of | B4: Paid | C4: Delivered | D4: Refunded | E4: Priority paid | F4: Unpaid holds | G4: Paid £ | H4: Fill vs 20 slots
A5: 2026-07-06 | B5: 2 | C5: 3 | D5: 0 | E5: 0 | F5: 1 | G5: 240 | H5: =B5/20
A6: 2026-07-27 | B6: 6 | C6: 2 | D6: 5 | E6: 0 | F6: 5 | G6: 720 | H6: =B6/20
A7: 2026-08-03 | B7: 3 | C7: 3 | D7: 0 | E7: 0 | F7: 3 | G7: 360 | H7: =B7/20
A8: 2026-08-10 | B8: 0 | C8: 0 | D8: 0 | E8: 0 | F8: 2 | G8: 0 | H8: =B8/20
A9: 2026-08-17 | B9: 15 | C9: 7 | D9: 6 | E9: 0 | F9: 2 | G9: 1800 | H9: =B9/20
A10: 2026-08-24 | B10: 7 | C10: 4 | D10: 0 | E10: 0 | F10: 8 | G10: 840 | H10: =B10/20
A11: 2026-08-31 | B11: 13 | C11: 5 | D11: 1 | E11: 0 | F11: 6 | G11: 1890 | H11: =B11/20
A12: 2026-09-07 | B12: 6 | C12: 3 | D12: 0 | E12: 0 | F12: 6 | G12: 900 | H12: =B12/20
A13: 2026-09-14 | B13: 6 | C13: 6 | D13: 0 | E13: 0 | F13: 0 | G13: 900 | H13: =B13/20
A14: 2026-09-21 | B14: 6 | C14: 4 | D14: 0 | E14: 1 | F14: 6 | G14: 940 | H14: =B14/20
A16: Since 17 Aug (6 weeks) | B16: =AVERAGE(B9:B14) | C16: =AVERAGE(C9:C14) | D16: =SUM(D9:D14)/SUM(B9:B14) | G16: =AVERAGE(G9:G14) | H16: =AVERAGE(H9:H14) | I16: avg paid/wk · avg delivered/wk · refund rate by count · avg paid £/wk · avg fill
A17: Last 3 weeks | B17: =AVERAGE(B12:B14) | C17: =AVERAGE(C12:C14) | G17: =AVERAGE(G12:G14) | H17: =AVERAGE(H12:H14)
A19: Tier mix since 1 Aug (paid cases): 20 legacy £120 · 24 Essential £150 · 1 Priority £190. Refunded: 7. Unpaid/expired holds: 27 — the diary looks fuller than revenue.
A20: Booking pattern: 70% of paid slots fall Mon–Fri 11:00–16:00 UK, peak Tue/Wed/Thu 12:00. Weekend mornings carry ~15%.

Sheet Sources
A1: Sources and known gaps
A3: Production DB | B3: Lovable project d454fddf (ila-hub.com) — cases table, queried 26 Sep 2026. Weekly paid/delivered/refunded, tier mix, slot hours.
A4: Pricing | B4: Daniel McAfee email 'New priority price ID', 23 Sep 2026 (£190 Priority). Granola catch-ups 8–24 Sep 2026 (£150 Essential, £25 wet-sign add-on).
A5: Commercial terms | B5: ILA Hub Master PRD v1.1, 11 May 2026 — §2 Commercial structure (60/40 split after direct costs, marketing off top, VAT threshold, refund policy).
A6: Targets | B6: Notion 'Business dashboard' (12 Sep 2026): £6k then £10k monthly net delivered revenue; paid→delivered 36.2% lifetime; refund 20.7% by value.
A7: Operating context | B7: Granola catch-ups Sep 2026: calls 10–15 min, ~90% of clients arrive without full documents, unpaid holds inflating diary, 2–3 extra lawyers targeted by Nov (excluded here by your brief).
A8: Gap — capacity | B8: Daniel's committed weekly slots were never recorded (dashboard item D12). This model uses your 18–22 range as the input.
A9: Gap — delivery lag | B9: Paid → delivered is counted in the month paid. Real delivery slips days to weeks (backlog ~15 matters at 6 Sep). Cash timing is therefore slightly optimistic in each month and neutral over 6 months.
A10: Gap — second guarantors | B10: Multi-guarantor matters generate extra bookings (each guarantor books a slot). Treated as ordinary slots; no separate uplift modelled.
